{
  "id": "002",
  "name": "阿尔托莉雅・潘德拉贡",
  "nameJP": "アルトリア・ペンドラゴン",
  "nameEN": "Artoria Pendragon",
  "fuzzyKeywords": [],
  "exactKeywords": [],
  "rarity": 5,
  "class": 1,
  "startATK": 1734,
  "endATK": 11221,
  "startHP": 2222,
  "endHP": 15150,
  "grailATK": 12283,
  "grailHP": 16597,
  "illustrator": "武内 崇",
  "cv": "川澄 綾子",
  "gender": 1,
  "attribute": 2,
  "alignment": "00",
  "cards": [
    2,
    2,
    1
  ],
  "hits": [
    2,
    1,
    2,
    3
  ],
  "charge": [
    0.0086,
    0.0086,
    0.0086,
    0.0086
  ],
  "starAbsorption": 102,
  "starGeneration": 0.1,
  "npChargeATK": 0.0086,
  "npChargeDEF": 0.03,
  "deathResist": 0.21,
  "traits": [],
  "skill1": [
    {
      "name": "领导力",
      "lv": "B",
      "initialCD": 7,
      "condition": 0,
      "effect": [
        {
          "id": "020000001000",
          "value": [
            9,
            9.9,
            10.8,
            11.7,
            12.6,
            13.5,
            14.4,
            15.3,
            16.2,
            18
          ],
          "duration": 3,
          "effectiveTime": -1,
          "phaseID": 0,
          "durationTime": 0,
          "probability": [
            100,
            0,
            0,
            0,
            0,
            0,
            0,
            0,
            0,
            0
          ]
        }
      ],
      "requirement": "00000",
      "img": 6
    }
  ],
  "skill2": [
    {
      "name": "魔力放出",
      "condition": 0,
      "lv": "B",
      "effect": [
        {
          "id": "000000001001",
          "value": [
            30,
            32,
            34,
            36,
            38,
            40,
            42,
            44,
            46,
            50
          ],
          "duration": 1,
          "durationTime": 0,
          "effectiveTime": -1,
          "phaseID": 0,
          "probability": [
            100,
            0,
            0,
            0,
            0,
            0,
            0,
            0,
            0,
            0
          ]
        }
      ],
      "initialCD": 7,
      "requirement": "00000",
      "img": 7
    }
  ],
  "skill3": [
    {
      "name": "直感",
      "condition": 0,
      "lv": "A",
      "effect": [
        {
          "id": "000000014005",
          "value": [
            5,
            6,
            7,
            8,
            9,
            10,
            11,
            12,
            13,
            15
          ],
          "duration": 0,
          "durationTime": 1,
          "effectiveTime": -1,
          "phaseID": 0,
          "probability": [
            100,
            0,
            0,
            0,
            0,
            0,
            0,
            0,
            0,
            0
          ]
        }
      ],
      "initialCD": 7,
      "requirement": "00000",
      "img": 8
    }
  ],
  "np": [
    {
      "name": "誓约胜利之剑",
      "type": 1,
      "condition": 0,
      "value": [
        300,
        400,
        450,
        475,
        500
      ],
      "card": 1,
      "lv": "A",
      "attackPhaseID": 0,
      "effect": [
        {
          "id": "000000004000",
          "value": [
            20,
            27.5,
            35,
            42.5,
            50
          ],
          "duration": 0,
          "durationTime": 1,
          "effectiveTime": -1,
          "phaseID": 1,
          "probability": [
            100,
            0,
            0,
            0,
            0,
            0,
            0,
            0,
            0,
            0
          ],
          "type": 2
        }
      ],
      "hits": 1
    },
    {
      "name": "誓约胜利之剑",
      "type": 1,
      "condition": 1,
      "value": [
        400,
        500,
        550,
        575,
        600
      ],
      "card": 1,
      "lv": "A++",
      "attackPhaseID": 0,
      "effect": [
        {
          "id": "000000004000",
          "value": [
            20,
            27.5,
            35,
            42.5,
            50
          ],
          "duration": 0,
          "durationTime": 1,
          "effectiveTime": -1,
          "phaseID": 1,
          "probability": [
            100,
            0,
            0,
            0,
            0,
            0,
            0,
            0,
            0,
            0
          ],
          "type": 2
        }
      ],
      "hits": 1
    }
  ],
  "classSkill": [
    {
      "name": "对魔力",
      "lv": "A",
      "effect": [
        {
          "id": "000000000001",
          "value": [
            20,
            0,
            0,
            0,
            0,
            0,
            0,
            0,
            0,
            0
          ],
          "duration": 99999,
          "durationTime": 0,
          "effectiveTime": -1,
          "phaseID": 0,
          "probability": [
            100,
            0,
            0,
            0,
            0,
            0,
            0,
            0,
            0,
            0
          ]
        }
      ],
      "img": 4
    },
    {
      "name": "骑乘",
      "lv": "B",
      "effect": [
        {
          "id": "000000001003",
          "value": [
            8,
            0,
            0,
            0,
            0,
            0,
            0,
            0,
            0,
            0
          ],
          "duration": 99999,
          "durationTime": 0,
          "effectiveTime": -1,
          "phaseID": 0,
          "probability": [
            100,
            0,
            0,
            0,
            0,
            0,
            0,
            0,
            0,
            0
          ]
        }
      ],
      "img": 5
    }
  ],
  "skillResource": [
    [
      {
        "id": "0000",
        "num": 5
      }
    ],
    [
      {
        "id": "0000",
        "num": 12
      }
    ],
    [
      {
        "id": "0100",
        "num": 5
      }
    ],
    [
      {
        "id": "0100",
        "num": 12
      },
      {
        "id": "1000",
        "num": 15
      }
    ],
    [
      {
        "id": "0200",
        "num": 5
      },
      {
        "id": "1000",
        "num": 29
      }
    ],
    [
      {
        "id": "0200",
        "num": 12
      },
      {
        "id": "1002",
        "num": 12
      }
    ],
    [
      {
        "id": "1002",
        "num": 24
      },
      {
        "id": "1200",
        "num": 4
      }
    ],
    [
      {
        "id": "1200",
        "num": 11
      },
      {
        "id": "1202",
        "num": 10
      }
    ],
    [
      {
        "id": "2000",
        "num": 1
      }
    ]
  ],
  "ascensionResource": [
    [
      {
        "id": "4000",
        "num": 5
      }
    ],
    [
      {
        "id": "4000",
        "num": 12
      },
      {
        "id": "1002",
        "num": 18
      }
    ],
    [
      {
        "id": "4100",
        "num": 5
      },
      {
        "id": "1104",
        "num": 4
      },
      {
        "id": "1000",
        "num": 29
      }
    ],
    [
      {
        "id": "4100",
        "num": 12
      },
      {
        "id": "1104",
        "num": 8
      },
      {
        "id": "1202",
        "num": 5
      }
    ]
  ],
  "illustratorEn": "Takeuchi Takashi",
  "cvEn": "Kawasumi Ayako"
}