{
  "id": "084",
  "name": "阿周那",
  "nameJP": "アルジュナ",
  "nameEN": "Arjuna",
  "fuzzyKeywords": [
    "阿周那",
    "Arjuna",
    "アルジュナ"
  ],
  "exactKeywords": [],
  "rarity": 5,
  "class": 2,
  "startATK": 1907,
  "endATK": 12342,
  "startHP": 1940,
  "endHP": 13230,
  "grailATK": 13510,
  "grailHP": 14494,
  "illustrator": "pako",
  "cv": "岛崎信长",
  "gender": 0,
  "attribute": 1,
  "alignment": "01",
  "cards": [
    3,
    1,
    1
  ],
  "hits": [
    3,
    3,
    2,
    5
  ],
  "charge": [
    0.0051,
    0.0051,
    0.0051,
    0.0051
  ],
  "starAbsorption": 154,
  "starGeneration": 0.08,
  "npChargeATK": 0.0051,
  "npChargeDEF": 0.03,
  "deathResist": 0.315,
  "traits": [],
  "skill1": [
    {
      "name": "千里眼",
      "condition": 0,
      "lv": "C+",
      "effect": [
        {
          "id": "000000000017",
          "value": [
            30,
            32,
            34,
            36,
            38,
            40,
            42,
            44,
            46,
            50
          ],
          "duration": 3,
          "durationTime": 0,
          "effectiveTime": -1,
          "phaseID": 0,
          "probability": [
            100,
            0,
            0,
            0,
            0,
            0,
            0,
            0,
            0,
            0
          ]
        }
      ],
      "initialCD": 8
    },
    {
      "name": "千里眼（射手）",
      "condition": 1,
      "lv": "B+",
      "effect": [
        {
          "id": "000000000017",
          "value": [
            30,
            32,
            34,
            36,
            38,
            40,
            42,
            44,
            46,
            50
          ],
          "duration": 3,
          "durationTime": 0,
          "effectiveTime": -1,
          "phaseID": 0,
          "probability": [
            100,
            0,
            0,
            0,
            0,
            0,
            0,
            0,
            0,
            0
          ]
        },
        {
          "id": "000000005007",
          "value": [
            0,
            0,
            0,
            0,
            0,
            0,
            0,
            0,
            0,
            0
          ],
          "duration": 5,
          "durationTime": 0,
          "effectiveTime": -1,
          "phaseID": 0,
          "probability": [
            100,
            0,
            0,
            0,
            0,
            0,
            0,
            0,
            0,
            0
          ]
        }
      ],
      "initialCD": 8
    }
  ],
  "skill2": [
    {
      "name": "天授的英雄",
      "condition": 0,
      "lv": "A",
      "effect": [
        {
          "id": "000000004000",
          "value": [
            25,
            0,
            0,
            0,
            0,
            0,
            0,
            0,
            0,
            0
          ],
          "duration": 0,
          "durationTime": 1,
          "effectiveTime": -1,
          "phaseID": 0,
          "probability": [
            100,
            0,
            0,
            0,
            0,
            0,
            0,
            0,
            0,
            0
          ]
        },
        {
          "id": "000000014011",
          "value": [
            1000,
            1100,
            1200,
            1300,
            1400,
            1500,
            1600,
            1700,
            1800,
            2000
          ],
          "duration": 5,
          "durationTime": 0,
          "effectiveTime": -1,
          "phaseID": 0,
          "probability": [
            100,
            0,
            0,
            0,
            0,
            0,
            0,
            0,
            0,
            0
          ]
        },
        {
          "id": "000000014006",
          "value": [
            4,
            5,
            5,
            6,
            6,
            6,
            7,
            7,
            8,
            8
          ],
          "duration": 5,
          "durationTime": 0,
          "effectiveTime": -1,
          "phaseID": 0,
          "probability": [
            100,
            0,
            0,
            0,
            0,
            0,
            0,
            0,
            0,
            0
          ]
        }
      ],
      "initialCD": 12
    }
  ],
  "skill3": [
    {
      "name": "魔力放出（炎）",
      "condition": 0,
      "lv": "A",
      "effect": [
        {
          "id": "000000001001",
          "value": [
            20,
            21,
            22,
            23,
            24,
            25,
            26,
            27,
            28,
            30
          ],
          "duration": 1,
          "durationTime": 0,
          "effectiveTime": -1,
          "phaseID": 0,
          "probability": [
            100,
            0,
            0,
            0,
            0,
            0,
            0,
            0,
            0,
            0
          ]
        },
        {
          "id": "000000001005",
          "value": [
            10,
            11,
            12,
            13,
            14,
            15,
            16,
            17,
            18,
            20
          ],
          "duration": 1,
          "durationTime": 0,
          "effectiveTime": -1,
          "phaseID": 0,
          "probability": [
            100,
            0,
            0,
            0,
            0,
            0,
            0,
            0,
            0,
            0
          ]
        }
      ],
      "initialCD": 7
    }
  ],
  "np": [
    {
      "name": "破坏神的手影（Pāśupata）",
      "type": 1,
      "condition": 0,
      "value": [
        300,
        400,
        450,
        475,
        500
      ],
      "card": 1,
      "lv": "A+",
      "attackPhaseID": 0,
      "effect": [
        {
          "id": "120000024012",
          "value": [
            0,
            0,
            0,
            0,
            0
          ],
          "duration": 0,
          "durationTime": 1,
          "effectiveTime": -1,
          "phaseID": "1",
          "probability": [
            30,
            0,
            0,
            0,
            0,
            0,
            0,
            0,
            0,
            0
          ],
          "type": 0
        },
        {
          "id": "120220024012",
          "value": [
            0,
            0,
            0,
            0,
            0
          ],
          "duration": 0,
          "durationTime": 1,
          "effectiveTime": -1,
          "phaseID": "1",
          "probability": [
            50,
            0,
            0,
            0,
            0,
            0,
            0,
            0,
            0,
            0
          ],
          "type": 0
        },
        {
          "id": "120000022000",
          "value": [
            20,
            25,
            30,
            35,
            40
          ],
          "duration": 3,
          "durationTime": 0,
          "effectiveTime": -1,
          "phaseID": "1",
          "probability": [
            100,
            0,
            0,
            0,
            0,
            0,
            0,
            0,
            0,
            0
          ],
          "type": 2
        }
      ],
      "hits": 1
    },
    {
      "name": "破坏神的手影（Pāśupata）",
      "type": 1,
      "condition": 1,
      "value": [
        400,
        500,
        550,
        575,
        600
      ],
      "card": 1,
      "lv": "A++",
      "attackPhaseID": 0,
      "effect": [
        {
          "id": "120000024012",
          "value": [
            0,
            0,
            0,
            0,
            0
          ],
          "duration": 0,
          "durationTime": 1,
          "effectiveTime": -1,
          "phaseID": "1",
          "probability": [
            50,
            0,
            0,
            0,
            0,
            0,
            0,
            0,
            0,
            0
          ],
          "type": 0
        },
        {
          "id": "120220024012",
          "value": [
            0,
            0,
            0,
            0,
            0
          ],
          "duration": 0,
          "durationTime": 1,
          "effectiveTime": -1,
          "phaseID": "1",
          "probability": [
            80,
            0,
            0,
            0,
            0,
            0,
            0,
            0,
            0,
            0
          ],
          "type": 0
        },
        {
          "id": "120000022000",
          "value": [
            20,
            25,
            30,
            35,
            40
          ],
          "duration": 3,
          "durationTime": 0,
          "effectiveTime": -1,
          "phaseID": "1",
          "probability": [
            100,
            0,
            0,
            0,
            0,
            0,
            0,
            0,
            0,
            0
          ],
          "type": 2
        }
      ],
      "hits": 1
    }
  ],
  "classSkill": [
    {
      "name": "对魔力",
      "lv": "C",
      "effect": [
        {
          "id": "000000000001",
          "value": [
            15,
            0,
            0,
            0,
            0,
            0,
            0,
            0,
            0,
            0
          ],
          "duration": 99999,
          "durationTime": 0,
          "effectiveTime": -1,
          "phaseID": 0,
          "probability": [
            100,
            0,
            0,
            0,
            0,
            0,
            0,
            0,
            0,
            0
          ]
        }
      ]
    },
    {
      "name": "单独行动",
      "lv": "A",
      "effect": [
        {
          "id": "000000001004",
          "value": [
            10,
            0,
            0,
            0,
            0,
            0,
            0,
            0,
            0,
            0
          ],
          "duration": 99999,
          "durationTime": 0,
          "effectiveTime": -1,
          "phaseID": 0,
          "probability": [
            100,
            0,
            0,
            0,
            0,
            0,
            0,
            0,
            0,
            0
          ]
        }
      ]
    },
    {
      "name": "神性",
      "lv": "B",
      "effect": [
        {
          "id": "000000011000",
          "value": [
            175,
            0,
            0,
            0,
            0,
            0,
            0,
            0,
            0,
            0
          ],
          "duration": 99999,
          "durationTime": 0,
          "effectiveTime": -1,
          "phaseID": 0,
          "probability": [
            100,
            0,
            0,
            0,
            0,
            0,
            0,
            0,
            0,
            0
          ]
        }
      ]
    }
  ],
  "skillResource": [
    [
      {
        "id": "0001",
        "num": 5
      }
    ],
    [
      {
        "id": "0001",
        "num": 12
      }
    ],
    [
      {
        "id": "0101",
        "num": 5
      }
    ],
    [
      {
        "id": "0101",
        "num": 12
      },
      {
        "id": "1104",
        "num": 4
      }
    ],
    [
      {
        "id": "0201",
        "num": 5
      },
      {
        "id": "1104",
        "num": 8
      }
    ],
    [
      {
        "id": "0201",
        "num": 12
      },
      {
        "id": "1000",
        "num": 15
      }
    ],
    [
      {
        "id": "1000",
        "num": 29
      },
      {
        "id": "1100",
        "num": 8
      }
    ],
    [
      {
        "id": "1100",
        "num": 22
      },
      {
        "id": "1201",
        "num": 10
      }
    ],
    [
      {
        "id": "2000",
        "num": 1
      }
    ]
  ],
  "ascensionResource": [
    [
      {
        "id": "4001",
        "num": 5
      }
    ],
    [
      {
        "id": "4001",
        "num": 12
      },
      {
        "id": "1000",
        "num": 22
      }
    ],
    [
      {
        "id": "4101",
        "num": 5
      },
      {
        "id": "1104",
        "num": 8
      },
      {
        "id": "1103",
        "num": 4
      }
    ],
    [
      {
        "id": "4101",
        "num": 12
      },
      {
        "id": "1103",
        "num": 8
      },
      {
        "id": "1201",
        "num": 5
      }
    ]
  ]
}